LICENSE
MANIFEST.in
README.rst
buildout.cfg
develop.cfg
pyproject.toml
requirements.txt
setup.py
version.txt
bob/__init__.py
bob.learn.linear.egg-info/PKG-INFO
bob.learn.linear.egg-info/SOURCES.txt
bob.learn.linear.egg-info/dependency_links.txt
bob.learn.linear.egg-info/entry_points.txt
bob.learn.linear.egg-info/not-zip-safe
bob.learn.linear.egg-info/requires.txt
bob.learn.linear.egg-info/top_level.txt
bob/learn/__init__.py
bob/learn/linear/GFK.py
bob/learn/linear/__init__.py
bob/learn/linear/auxiliary.py
bob/learn/linear/bic.cpp
bob/learn/linear/lda.cpp
bob/learn/linear/logreg.cpp
bob/learn/linear/machine.cpp
bob/learn/linear/main.cpp
bob/learn/linear/pca.cpp
bob/learn/linear/test.py
bob/learn/linear/test_bic.py
bob/learn/linear/test_gfk.py
bob/learn/linear/test_picklability.py
bob/learn/linear/version.cpp
bob/learn/linear/wccn.cpp
bob/learn/linear/whitening.cpp
bob/learn/linear/cpp/bic.cpp
bob/learn/linear/cpp/lda.cpp
bob/learn/linear/cpp/logreg.cpp
bob/learn/linear/cpp/machine.cpp
bob/learn/linear/cpp/pca.cpp
bob/learn/linear/cpp/wccn.cpp
bob/learn/linear/cpp/whitening.cpp
bob/learn/linear/data/dslr.mat
bob/learn/linear/data/dslr.mat.hdf5
bob/learn/linear/data/dslr_labels.mat
bob/learn/linear/data/dslr_labels.mat.hdf5
bob/learn/linear/data/linear-test.hdf5
bob/learn/linear/data/negatives_isv.hdf5
bob/learn/linear/data/negatives_lda.hdf5
bob/learn/linear/data/positives_isv.hdf5
bob/learn/linear/data/positives_lda.hdf5
bob/learn/linear/data/webcam.mat
bob/learn/linear/data/webcam.mat.hdf5
bob/learn/linear/data/webcam_labels.mat
bob/learn/linear/data/webcam_labels.mat.hdf5
bob/learn/linear/include/bob.learn.linear/api.h
bob/learn/linear/include/bob.learn.linear/bic.h
bob/learn/linear/include/bob.learn.linear/config.h
bob/learn/linear/include/bob.learn.linear/lda.h
bob/learn/linear/include/bob.learn.linear/logreg.h
bob/learn/linear/include/bob.learn.linear/machine.h
bob/learn/linear/include/bob.learn.linear/pca.h
bob/learn/linear/include/bob.learn.linear/wccn.h
bob/learn/linear/include/bob.learn.linear/whitening.h
doc/c_cpp_api.rst
doc/conf.py
doc/guide.rst
doc/index.rst
doc/links.rst
doc/py_api.rst